nl2elem_to_csv/__init__.py
nl2elem_to_csv/__main__.py
nl2elem_to_csv/csv_writer.py
nl2elem_to_csv/data_processor.py
nl2elem_to_csv/nl2elem_reader.py
nl2elem_to_csv-0.1.6.dist-info/LICENSE
nl2elem_to_csv-0.1.6.dist-info/METADATA
nl2elem_to_csv-0.1.6.dist-info/WHEEL
nl2elem_to_csv-0.1.6.dist-info/entry_points.txt
nl2elem_to_csv-0.1.6.dist-info/top_level.txt
nl2elem_to_csv-0.1.6.dist-info/RECORD
